neural_ssm/__init__.py
neural_ssm/rens/__init__.py
neural_ssm/rens/ren.py
neural_ssm/ssm/__init__.py
neural_ssm/ssm/experimental.py
neural_ssm/ssm/lru.py
neural_ssm/ssm/mamba.py
neural_ssm/ssm/scan_utils.py
neural_ssm/static_layers/__init__.py
neural_ssm/static_layers/generic_layers.py
neural_ssm/static_layers/lipschitz_mlps.py
neural_ssm-0.26.dist-info/METADATA
neural_ssm-0.26.dist-info/WHEEL
neural_ssm-0.26.dist-info/top_level.txt
neural_ssm-0.26.dist-info/RECORD
