Metadata-Version: 2.4
Name: neural-ssm
Version: 0.26
Summary: Neural state space models and LRU variants in PyTorch
Author: Leonardo Massai
License: MIT
Project-URL: Homepage, https://github.com/LeoMassai
Project-URL: Repository, https://github.com/LeoMassai/neural-ssm
Project-URL: Issues, https://github.com/LeoMassai/neural-ssm/issues
Classifier: Programming Language :: Python :: 3
Classifier: Programming Language :: Python :: 3 :: Only
Classifier: Programming Language :: Python :: 3.9
Classifier: Programming Language :: Python :: 3.10
Classifier: Programming Language :: Python :: 3.11
Classifier: Programming Language :: Python :: 3.12
Classifier: License :: OSI Approved :: MIT License
Classifier: Operating System :: OS Independent
Classifier: Intended Audience :: Science/Research
Classifier: Topic :: Scientific/Engineering :: Artificial Intelligence
Requires-Python: >=3.9
Requires-Dist: torch>=2.2
Requires-Dist: numpy>=1.23
Requires-Dist: tqdm>=4.66
Requires-Dist: matplotlib>=3.7
Requires-Dist: einops>=0.6
Requires-Dist: typing-extensions>=4.5
Requires-Dist: jax>=0.4.26
Requires-Dist: jaxlib>=0.4.26
Requires-Dist: deel-torchlip
Provides-Extra: dev
Requires-Dist: black>=24.3.0; extra == "dev"
Requires-Dist: ruff>=0.3.0; extra == "dev"
Requires-Dist: mypy>=1.6.0; extra == "dev"
Requires-Dist: pytest>=7.4; extra == "dev"
Requires-Dist: pytest-cov>=4.1; extra == "dev"
Requires-Dist: ipykernel>=6.29; extra == "dev"
Requires-Dist: jupyter>=1.0; extra == "dev"
Provides-Extra: examples
Requires-Dist: seaborn>=0.13; extra == "examples"
Requires-Dist: pandas>=2.1; extra == "examples"
Provides-Extra: docs
Requires-Dist: mkdocs>=1.5; extra == "docs"
Requires-Dist: mkdocs-material>=9.5; extra == "docs"
